{"cameraMode":{"drawMode":0,"name":"Shaded","section":"Shading Mode"},"sceneLighting":false,"audioPlay":false,"sceneViewState":{"m_AlwaysRefresh":false,"showFog":true,"showSkybox":false,"showFlares":true,"showImageEffects":true,"showParticleSystems":true,"showVisualEffectGraphs":true,"m_FxEnabled":true},"in2DMode":false,"pivot":{"x":11.229989051818848,"y":0.22480270266532899,"z":-4.1553955078125},"rotation":{"x":0.07060948759317398,"y":0.06310983747243881,"z":-0.0044792150147259239,"w":0.9954846501350403},"size":1.2247449159622193,"orthographic":false}